{"visits":408,"/la-armadura-de-dios":45,"/":944,"/videos-de-pablito-el-pequeno-misionero":80,"/el-celular":196,"/videos-reino-de-los-cielos-inicio":52,"/como-educar":13,"/enfoque-a-la-familia":22,"/folletos":13,"/Folleto-una-ninez-con-el-proposito-de-dios":3,"/biblia-infantil":24,"/concurso-canciones":22,"/contenido":44,"/juegos-super-libro":67,"/una-ninez-con-el-proposito-de-dios":20,"/videos-el-castigo":51,"/el-infierno":216,"/el-amor":16,"/el-reino-de-los-cielos":95,"/videos-que-promueven-valores":15,"/nacer-de-nuevo":72,"/videos-el-infierno":92,"/proyectos":7,"/historia":31,"/jovenes-constructores-de-paz-y-amor":12,"/folleto-la-armadura-de-dios":9,"/escuela-para-padres":22,"/madres-triunfadoras":44,"/videos-una-ninez-con-el-proposito-de-dios":18,"/videos-canciones-biblicas-pequenos-heroes":22,"/satanas-es-real":59,"/videos-satanas-es-real":45,"/videos-el-celular":23,"/el-mundo-y-sus-tendencias":18,"/videos-el-mundo-y-sus-tendencias":8,"/la-inmoralidad":30,"/videos-la-inmoralidad":4,"/videos-el-reino-de-los-cielos":15,"/videos-la-armadura-de-dios":15,"/videos-nacer-de-nuevo":3,"/videos-la-creacion":11,"/videos-el-amor":10,"/testimonios-ex-sicarios":13,"/el-abuso":36,"/videos-historias-biblicas-pequenos-heroes":21,"/memorizando-versiculos":48,"/videos-el-superlibro":21,"/testimonios-ex-homosexuales":38,"/el-jardin-con-el-amor-de-dios":16,"/folleto-como-ayudar-a-sus-hijos":10,"/concurso-memoria":7,"/aprende-sobre-jesus":17,"/caricaturas-peligrosas":5,"/halloween":18,"/ouija":21,"/unete":3,"/testimonios-ex-lesbianas":34,"/investiganos":36,"/la-idolatria":5,"/periodicos":12,"/videos-el-abuso":6,"/testimonios-ex-brujos":2,"/informacion-corporativa":1,"/folleto-curso-para-capacitadores":5,"/folleto-jesucristo":1,"/videos-versiculos-para-memorizar":4,"/folleto-la-prevencion":2,"/fundador":26,"/consursos":2,"/testimonios-ex-prostitutas":12,"/testimonios-ex-transgenero":8,"/folleto-libretos":3,"/folleto-una-ninez-con-el-proposito-de-dios":3,"/investiganos/":1,"/videos-la-idolatria":1}