{"visits":408,"/la-armadura-de-dios":72,"/":1315,"/videos-de-pablito-el-pequeno-misionero":101,"/el-celular":263,"/videos-reino-de-los-cielos-inicio":107,"/como-educar":23,"/enfoque-a-la-familia":59,"/folletos":42,"/Folleto-una-ninez-con-el-proposito-de-dios":20,"/biblia-infantil":27,"/concurso-canciones":78,"/contenido":59,"/juegos-super-libro":115,"/una-ninez-con-el-proposito-de-dios":29,"/videos-el-castigo":64,"/el-infierno":302,"/el-amor":35,"/el-reino-de-los-cielos":134,"/videos-que-promueven-valores":69,"/nacer-de-nuevo":126,"/videos-el-infierno":110,"/proyectos":9,"/historia":68,"/jovenes-constructores-de-paz-y-amor":30,"/folleto-la-armadura-de-dios":20,"/escuela-para-padres":57,"/madres-triunfadoras":89,"/videos-una-ninez-con-el-proposito-de-dios":19,"/videos-canciones-biblicas-pequenos-heroes":27,"/satanas-es-real":68,"/videos-satanas-es-real":71,"/videos-el-celular":156,"/el-mundo-y-sus-tendencias":33,"/videos-el-mundo-y-sus-tendencias":17,"/la-inmoralidad":70,"/videos-la-inmoralidad":20,"/videos-el-reino-de-los-cielos":27,"/videos-la-armadura-de-dios":28,"/videos-nacer-de-nuevo":20,"/videos-la-creacion":24,"/videos-el-amor":20,"/testimonios-ex-sicarios":29,"/el-abuso":49,"/videos-historias-biblicas-pequenos-heroes":30,"/memorizando-versiculos":58,"/videos-el-superlibro":48,"/testimonios-ex-homosexuales":69,"/el-jardin-con-el-amor-de-dios":32,"/folleto-como-ayudar-a-sus-hijos":21,"/concurso-memoria":37,"/aprende-sobre-jesus":18,"/caricaturas-peligrosas":14,"/halloween":26,"/ouija":26,"/unete":9,"/testimonios-ex-lesbianas":57,"/investiganos":109,"/la-idolatria":16,"/periodicos":34,"/videos-el-abuso":26,"/testimonios-ex-brujos":9,"/informacion-corporativa":7,"/folleto-curso-para-capacitadores":14,"/folleto-jesucristo":22,"/videos-versiculos-para-memorizar":10,"/folleto-la-prevencion":9,"/fundador":98,"/consursos":11,"/testimonios-ex-prostitutas":25,"/testimonios-ex-transgenero":29,"/folleto-libretos":13,"/folleto-una-ninez-con-el-proposito-de-dios":9,"/investiganos/":1,"/videos-la-idolatria":16,"/para-colorear-y-memorizar":10,"/folletos/":1,"/el-jardin-con-el-amor-de-dios/":2,"/jovenes-constructores-de-paz-y-amor/":1,"/apadrinamiento":4,"/familias-del-reino-animal":1,"/cartelera-sobre-valores-para-imprimir":1}