{"visits":408,"/la-armadura-de-dios":53,"/":1067,"/videos-de-pablito-el-pequeno-misionero":83,"/el-celular":222,"/videos-reino-de-los-cielos-inicio":66,"/como-educar":16,"/enfoque-a-la-familia":29,"/folletos":23,"/Folleto-una-ninez-con-el-proposito-de-dios":10,"/biblia-infantil":26,"/concurso-canciones":43,"/contenido":44,"/juegos-super-libro":78,"/una-ninez-con-el-proposito-de-dios":25,"/videos-el-castigo":58,"/el-infierno":240,"/el-amor":24,"/el-reino-de-los-cielos":109,"/videos-que-promueven-valores":22,"/nacer-de-nuevo":101,"/videos-el-infierno":105,"/proyectos":9,"/historia":45,"/jovenes-constructores-de-paz-y-amor":20,"/folleto-la-armadura-de-dios":13,"/escuela-para-padres":35,"/madres-triunfadoras":63,"/videos-una-ninez-con-el-proposito-de-dios":19,"/videos-canciones-biblicas-pequenos-heroes":26,"/satanas-es-real":62,"/videos-satanas-es-real":51,"/videos-el-celular":136,"/el-mundo-y-sus-tendencias":25,"/videos-el-mundo-y-sus-tendencias":10,"/la-inmoralidad":41,"/videos-la-inmoralidad":10,"/videos-el-reino-de-los-cielos":21,"/videos-la-armadura-de-dios":20,"/videos-nacer-de-nuevo":8,"/videos-la-creacion":16,"/videos-el-amor":15,"/testimonios-ex-sicarios":24,"/el-abuso":43,"/videos-historias-biblicas-pequenos-heroes":23,"/memorizando-versiculos":48,"/videos-el-superlibro":32,"/testimonios-ex-homosexuales":49,"/el-jardin-con-el-amor-de-dios":30,"/folleto-como-ayudar-a-sus-hijos":14,"/concurso-memoria":11,"/aprende-sobre-jesus":18,"/caricaturas-peligrosas":9,"/halloween":19,"/ouija":22,"/unete":5,"/testimonios-ex-lesbianas":41,"/investiganos":55,"/la-idolatria":12,"/periodicos":21,"/videos-el-abuso":11,"/testimonios-ex-brujos":4,"/informacion-corporativa":2,"/folleto-curso-para-capacitadores":9,"/folleto-jesucristo":6,"/videos-versiculos-para-memorizar":4,"/folleto-la-prevencion":5,"/fundador":47,"/consursos":3,"/testimonios-ex-prostitutas":19,"/testimonios-ex-transgenero":14,"/folleto-libretos":9,"/folleto-una-ninez-con-el-proposito-de-dios":5,"/investiganos/":1,"/videos-la-idolatria":5,"/para-colorear-y-memorizar":9,"/folletos/":1,"/el-jardin-con-el-amor-de-dios/":2,"/jovenes-constructores-de-paz-y-amor/":1,"/apadrinamiento":2,"/familias-del-reino-animal":1,"/cartelera-sobre-valores-para-imprimir":1}