{"visits":408,"/la-armadura-de-dios":143,"/":2004,"/videos-de-pablito-el-pequeno-misionero":137,"/el-celular":362,"/videos-reino-de-los-cielos-inicio":167,"/como-educar":36,"/enfoque-a-la-familia":102,"/folletos":113,"/Folleto-una-ninez-con-el-proposito-de-dios":31,"/biblia-infantil":35,"/concurso-canciones":127,"/contenido":66,"/juegos-super-libro":225,"/una-ninez-con-el-proposito-de-dios":34,"/videos-el-castigo":99,"/el-infierno":485,"/el-amor":56,"/el-reino-de-los-cielos":203,"/videos-que-promueven-valores":102,"/nacer-de-nuevo":180,"/videos-el-infierno":140,"/proyectos":9,"/historia":144,"/jovenes-constructores-de-paz-y-amor":36,"/folleto-la-armadura-de-dios":35,"/escuela-para-padres":84,"/madres-triunfadoras":118,"/videos-una-ninez-con-el-proposito-de-dios":22,"/videos-canciones-biblicas-pequenos-heroes":32,"/satanas-es-real":114,"/videos-satanas-es-real":120,"/videos-el-celular":187,"/el-mundo-y-sus-tendencias":64,"/videos-el-mundo-y-sus-tendencias":33,"/la-inmoralidad":100,"/videos-la-inmoralidad":34,"/videos-el-reino-de-los-cielos":40,"/videos-la-armadura-de-dios":42,"/videos-nacer-de-nuevo":39,"/videos-la-creacion":52,"/videos-el-amor":27,"/testimonios-ex-sicarios":71,"/el-abuso":85,"/videos-historias-biblicas-pequenos-heroes":36,"/memorizando-versiculos":93,"/videos-el-superlibro":113,"/testimonios-ex-homosexuales":145,"/el-jardin-con-el-amor-de-dios":51,"/folleto-como-ayudar-a-sus-hijos":42,"/concurso-memoria":101,"/aprende-sobre-jesus":28,"/caricaturas-peligrosas":20,"/halloween":49,"/ouija":54,"/unete":13,"/testimonios-ex-lesbianas":97,"/investiganos":175,"/la-idolatria":33,"/periodicos":94,"/videos-el-abuso":51,"/testimonios-ex-brujos":29,"/informacion-corporativa":12,"/folleto-curso-para-capacitadores":41,"/folleto-jesucristo":30,"/videos-versiculos-para-memorizar":15,"/folleto-la-prevencion":20,"/fundador":166,"/consursos":14,"/testimonios-ex-prostitutas":74,"/testimonios-ex-transgenero":112,"/folleto-libretos":27,"/folleto-una-ninez-con-el-proposito-de-dios":11,"/investiganos/":1,"/videos-la-idolatria":33,"/para-colorear-y-memorizar":14,"/folletos/":1,"/el-jardin-con-el-amor-de-dios/":2,"/jovenes-constructores-de-paz-y-amor/":1,"/apadrinamiento":11,"/familias-del-reino-animal":1,"/cartelera-sobre-valores-para-imprimir":3,"/el-infierno/":4,"/para-colorear-el-reino-de-los-cielos":1,"/dia-del-nino-para-colorear":2,"/cartelera-patios-para-imprimir":23,"/testimonios-ex-drogadictos":46,"/testimonios-ex-satanistas":12}